dekespo_ai_sdk/__init__.py
dekespo_ai_sdk/algorithms/__init__.py
dekespo_ai_sdk/algorithms/connected_component_labelling.py
dekespo_ai_sdk/algorithms/graph_search/__init__.py
dekespo_ai_sdk/algorithms/graph_search/api.py
dekespo_ai_sdk/algorithms/graph_search/breadth_first_search.py
dekespo_ai_sdk/algorithms/graph_search/depth_first_search.py
dekespo_ai_sdk/algorithms/graph_search/utils.py
dekespo_ai_sdk/core/__init__.py
dekespo_ai_sdk/core/assertion.py
dekespo_ai_sdk/core/dimensions.py
dekespo_ai_sdk/core/disjoint_set.py
dekespo_ai_sdk/core/graph.py
dekespo_ai_sdk/core/neighbour.py
dekespo_ai_sdk/core/raw_data_handler.py
dekespo_ai_sdk/core/shapes.py
dekespo_ai_sdk/core/utils.py
dekespo_ai_sdk/physics/__init__.py
dekespo_ai_sdk/physics/motion.py
dekespo_ai_sdk-1.0.2.dist-info/LICENSE
dekespo_ai_sdk-1.0.2.dist-info/METADATA
dekespo_ai_sdk-1.0.2.dist-info/WHEEL
dekespo_ai_sdk-1.0.2.dist-info/top_level.txt
dekespo_ai_sdk-1.0.2.dist-info/RECORD
