Metadata-Version: 2.1
Name: dekespo-ai-sdk
Version: 1.0.2
Summary: Dekespo AI SDK tools
Home-page: https://github.com/dekespo/dekespo_ai_sdk_py
Author: Deniz Kennedy
Author-email: denizkennedy@gmail.com
License: apache-2.0
Keywords: SDK,AI,Tool
Platform: UNKNOWN
Classifier: Intended Audience :: Developers
Classifier: License :: OSI Approved :: Apache Software License
Classifier: Programming Language :: Python :: 3
Classifier: Operating System :: OS Independent
Requires-Python: >=3.7
